statequark/__init__.py
statequark/batch.py
statequark/config.py
statequark/derived.py
statequark/executor.py
statequark/factory.py
statequark/logger.py
statequark/py.typed
statequark/quark.py
statequark/store.py
statequark/types.py
statequark/utils/__init__.py
statequark/utils/family.py
statequark/utils/history.py
statequark/utils/loadable.py
statequark/utils/middleware.py
statequark/utils/reducer.py
statequark/utils/select.py
statequark/utils/storage.py
statequark/utils/timing.py
statequark/utils/validate.py
statequark-0.5.3.dist-info/licenses/LICENSE
statequark-0.5.3.dist-info/METADATA
statequark-0.5.3.dist-info/WHEEL
statequark-0.5.3.dist-info/top_level.txt
statequark-0.5.3.dist-info/RECORD
